<?xml version="1.0" encoding="utf-8"?>
<partyTemplates>
    <MBPartyTemplate id="athen_party_template">
      <stacks>
        <PartyTemplateStack min_value="3" max_value="8" troop="NPCCharacter.athen_warrior" />
        <PartyTemplateStack min_value="3" max_value="8" troop="NPCCharacter.athen_soldier" />
        <PartyTemplateStack min_value="3" max_value="8" troop="NPCCharacter.athen_elite_soldier" />
        <PartyTemplateStack min_value="3" max_value="8" troop="NPCCharacter.athen_archer" />
        <PartyTemplateStack min_value="3" max_value="8" troop="NPCCharacter.athen_elite_archer" />		
      </stacks>
    </MBPartyTemplate>
</partyTemplates>
